pyckmeans/__init__.py
pyckmeans/core/__init__.py
pyckmeans/core/ckmeans.py
pyckmeans/core/multickmeans.py
pyckmeans/core/utils.py
pyckmeans/core/wecr.py
pyckmeans/distance/__init__.py
pyckmeans/distance/c_interop.py
pyckmeans/distance/lib/distance.so
pyckmeans/io/__init__.py
pyckmeans/io/c_interop.py
pyckmeans/io/csv.py
pyckmeans/io/fasta.py
pyckmeans/io/nucleotide_alignment.py
pyckmeans/io/phylip.py
pyckmeans/io/lib/nucencode.so
pyckmeans/knee/__init__.py
pyckmeans/ordering/__init__.py
pyckmeans/ordination/__init__.py
pyckmeans/ordination/utils.py
pyckmeans/utils/__init__.py
pyckmeans/utils/plotting.py
pyckmeans/utils/progressbar.py
pyckmeans-0.9.4.dist-info/LICENSE
pyckmeans-0.9.4.dist-info/METADATA
pyckmeans-0.9.4.dist-info/WHEEL
pyckmeans-0.9.4.dist-info/top_level.txt
pyckmeans-0.9.4.dist-info/RECORD
