Metadata-Version: 2.1
Name: pyckmeans
Version: 0.9.4
Summary: A consensus K-Means implementation.
Home-page: https://github.com/TankredO/pyckmeans
Author: Tankred Ott
License: UNKNOWN
Platform: any
Requires-Python: >=3.6
License-File: LICENSE
